{
  "text": [
    {
      "text": "Οι υπηρεσίες μας",
      "variant": "h2"
    },
    {      
      "text": "Συμπεριφορά, φιλοξενία και αποκατάσταση.",
      "color": "beta",
      "variant": "h4"
    },
      {      
    "text": "Ξεχωριστά ή συνδυαστικά.",
    "color": "gray",
    "variant": "h5"
  }

  ],
  "icon": {
    "src": "../../../assets/flexiblocks/icons/bx-analyse.svg",
    "alt": "alt text"
  },
  "collection": [
    {
      "images": [
        {
          "src": "../../../assets/flexiblocks/images/services/training.png",
          "alt": "Training service"
        }
      ],
      "text": [
        {
          "text": "Εκπαίδευση",
          "color": "alpha",
          "variant": "h3"
        },
        {
          "text": "Σχέδιο, επιστήμη & επιτυχία, χωρίς βία."
        }
      ],
      "buttons": [
        {
          "text": "Καθοδήγησε →",
          "type": "PAGE",
          "url": "/training",
          "variant": "secondary"
        }
      ]
    },
    {
      "images": [
        {
          "src": "../../../assets/flexiblocks/images/services/boarding.png",
          "alt": "Boarding service"
        }
      ],
      "text": [
        {
          "text": "Ξενοδοχείο",
          "color": "alpha",
          "variant": "h3"
        },
        {
          "text": "Το καλύτερο ξενοδοχείο σκύλων στην Θεσσαλονική."
        }
      ],
      "buttons": [
        {
          "text": "Μείνε →",
          "type": "PAGE",
          "url": "/boarding",
          "variant": "secondary"
        }
      ]
    },
    {
      "images": [
        {
          "src": "../../../assets/flexiblocks/images/services/rehab.png",
          "alt": "Rehab service"
        }
      ],
      "text": [
        {
          "text": "Αποκατάσταση",
          "color": "alpha",
          "variant": "h3"
        },
        {
          "text": "Φυσικοθεραπεία, υδροθεραπεία, αποκατάσταση & εκγύμνανση."
        }
      ],
      "buttons": [
        {
          "text": "Βελτίωσε →",
          "type": "PAGE",
          "url": "/rehab",
          "variant": "secondary"
        }
      ]
    },
    {
      "images": [
        {
          "src": "../../../assets/flexiblocks/images/services/academy.png",
          "alt": "Academy service"
        }
      ],
      "text": [
        {
          "text": "Ακαδημία Εκπαιδευτών",
          "color": "alpha",
          "variant": "h3"
        },
        {
          "text": "Γίνε εκπαιδευτής & ξεκλείδωσε τα μυστικά της συμπεριφοράς σκύλων."
        }
      ],
      "buttons": [
        {
          "text": "Μάθε →",
          "type": "PAGE",
          "url": "/academy",
          "variant": "secondary"
        }
      ]
    }
  ]
}